mkdocstrings_csharp-0.2.0.dist-info/METADATA
mkdocstrings_csharp-0.2.0.dist-info/WHEEL
mkdocstrings_csharp-0.2.0.dist-info/entry_points.txt
mkdocstrings_csharp-0.2.0.dist-info/licenses/LICENSE
mkdocstrings_handlers/csharp/__init__.py
mkdocstrings_handlers/csharp/debug.py
mkdocstrings_handlers/csharp/handler.py
mkdocstrings_handlers/csharp/py.typed
mkdocstrings_csharp-0.2.0.dist-info/RECORD
